<?xml version="1.0" encoding="UTF-8"?>
<fmiModelDescription
  xmlns:xsi="http://www.w3.org/2001/XMLSchema-instance"
  fmiVersion="2.0"
  modelName="Masterthesis.Models.mimo_processmodel"
  guid="{c89f1515-3a3d-4b8d-ada3-e0e2a68c1461}"
  description="Processmodel for a multiple input, multiple output system"
  generationTool="Dymola Version 2017 FD01 (64-bit), 2016-10-11 (requires license to execute)"
  generationDateAndTime="2017-09-16T14:11:30Z"
  variableNamingConvention="structured"
  numberOfEventIndicators="0">
  <ModelExchange
    modelIdentifier="Masterthesis_Models_mimo_0processmodel"
    canGetAndSetFMUstate="true"
    providesDirectionalDerivative="true"/>
  <TypeDefinitions>
    <SimpleType
      name="Modelica.Blocks.Interfaces.RealInput">
      <Real/>
    </SimpleType>
    <SimpleType
      name="Modelica.Blocks.Interfaces.RealOutput">
      <Real/>
    </SimpleType>
    <SimpleType
      name="Modelica.Blocks.Interfaces.RealVectorInput">
      <Real/>
    </SimpleType>
    <SimpleType
      name="Modelica.SIunits.Time">
      <Real
        quantity="Time"
        unit="s"/>
    </SimpleType>
  </TypeDefinitions>
  <DefaultExperiment startTime="0.0"
    stopTime="1.0"
    tolerance="0.0001"/>
  <ModelVariables>
    <!-- Index for next variable = 1 -->
    <ScalarVariable
      name="num[1,1,1]"
      valueReference="16777216"
      description="Numerator of the system"
      causality="parameter"
      variability="fixed">
      <Real start="0.001"/>
    </ScalarVariable>
    <!-- Index for next variable = 2 -->
    <ScalarVariable
      name="num[1,2,1]"
      valueReference="16777217"
      description="Numerator of the system"
      causality="parameter"
      variability="fixed">
      <Real start="0.001"/>
    </ScalarVariable>
    <!-- Index for next variable = 3 -->
    <ScalarVariable
      name="num[2,1,1]"
      valueReference="16777218"
      description="Numerator of the system"
      causality="parameter"
      variability="fixed">
      <Real start="0.001"/>
    </ScalarVariable>
    <!-- Index for next variable = 4 -->
    <ScalarVariable
      name="num[2,2,1]"
      valueReference="16777219"
      description="Numerator of the system"
      causality="parameter"
      variability="fixed">
      <Real start="0.001"/>
    </ScalarVariable>
    <!-- Index for next variable = 5 -->
    <ScalarVariable
      name="den[1,1,1]"
      valueReference="16777220"
      description="Denominator of the system"
      causality="parameter"
      variability="fixed">
      <Real start="0.001"/>
    </ScalarVariable>
    <!-- Index for next variable = 6 -->
    <ScalarVariable
      name="den[1,1,2]"
      valueReference="16777221"
      description="Denominator of the system"
      causality="parameter"
      variability="fixed">
      <Real start="0.001"/>
    </ScalarVariable>
    <!-- Index for next variable = 7 -->
    <ScalarVariable
      name="den[1,1,3]"
      valueReference="16777222"
      description="Denominator of the system"
      causality="parameter"
      variability="fixed">
      <Real start="0.001"/>
    </ScalarVariable>
    <!-- Index for next variable = 8 -->
    <ScalarVariable
      name="den[1,2,1]"
      valueReference="16777223"
      description="Denominator of the system"
      causality="parameter"
      variability="fixed">
      <Real start="0.001"/>
    </ScalarVariable>
    <!-- Index for next variable = 9 -->
    <ScalarVariable
      name="den[1,2,2]"
      valueReference="16777224"
      description="Denominator of the system"
      causality="parameter"
      variability="fixed">
      <Real start="0.001"/>
    </ScalarVariable>
    <!-- Index for next variable = 10 -->
    <ScalarVariable
      name="den[1,2,3]"
      valueReference="16777225"
      description="Denominator of the system"
      causality="parameter"
      variability="fixed">
      <Real start="0.001"/>
    </ScalarVariable>
    <!-- Index for next variable = 11 -->
    <ScalarVariable
      name="den[2,1,1]"
      valueReference="16777226"
      description="Denominator of the system"
      causality="parameter"
      variability="fixed">
      <Real start="0.001"/>
    </ScalarVariable>
    <!-- Index for next variable = 12 -->
    <ScalarVariable
      name="den[2,1,2]"
      valueReference="16777227"
      description="Denominator of the system"
      causality="parameter"
      variability="fixed">
      <Real start="0.001"/>
    </ScalarVariable>
    <!-- Index for next variable = 13 -->
    <ScalarVariable
      name="den[2,1,3]"
      valueReference="16777228"
      description="Denominator of the system"
      causality="parameter"
      variability="fixed">
      <Real start="0.001"/>
    </ScalarVariable>
    <!-- Index for next variable = 14 -->
    <ScalarVariable
      name="den[2,2,1]"
      valueReference="16777229"
      description="Denominator of the system"
      causality="parameter"
      variability="fixed">
      <Real start="0.001"/>
    </ScalarVariable>
    <!-- Index for next variable = 15 -->
    <ScalarVariable
      name="den[2,2,2]"
      valueReference="16777230"
      description="Denominator of the system"
      causality="parameter"
      variability="fixed">
      <Real start="0.001"/>
    </ScalarVariable>
    <!-- Index for next variable = 16 -->
    <ScalarVariable
      name="den[2,2,3]"
      valueReference="16777231"
      description="Denominator of the system"
      causality="parameter"
      variability="fixed">
      <Real start="0.001"/>
    </ScalarVariable>
    <!-- Index for next variable = 17 -->
    <ScalarVariable
      name="delay[1,1]"
      valueReference="16777232"
      description="Delay of the system for every transfer function"
      causality="parameter"
      variability="fixed">
      <Real start="0"/>
    </ScalarVariable>
    <!-- Index for next variable = 18 -->
    <ScalarVariable
      name="delay[1,2]"
      valueReference="16777233"
      description="Delay of the system for every transfer function"
      causality="parameter"
      variability="fixed">
      <Real start="0"/>
    </ScalarVariable>
    <!-- Index for next variable = 19 -->
    <ScalarVariable
      name="delay[2,1]"
      valueReference="16777234"
      description="Delay of the system for every transfer function"
      causality="parameter"
      variability="fixed">
      <Real start="0"/>
    </ScalarVariable>
    <!-- Index for next variable = 20 -->
    <ScalarVariable
      name="delay[2,2]"
      valueReference="16777235"
      description="Delay of the system for every transfer function"
      causality="parameter"
      variability="fixed">
      <Real start="0"/>
    </ScalarVariable>
    <!-- Index for next variable = 21 -->
    <ScalarVariable
      name="u[1]"
      valueReference="352321536"
      description="Systems set point"
      causality="input">
      <Real
        declaredType="Modelica.Blocks.Interfaces.RealInput"
        start="0.0"/>
    </ScalarVariable>
    <!-- Index for next variable = 22 -->
    <ScalarVariable
      name="u[2]"
      valueReference="352321537"
      description="Systems set point"
      causality="input">
      <Real
        declaredType="Modelica.Blocks.Interfaces.RealInput"
        start="0.0"/>
    </ScalarVariable>
    <!-- Index for next variable = 23 -->
    <ScalarVariable
      name="y[1]"
      valueReference="335544320"
      description="Systems real output"
      causality="output">
      <Real
        declaredType="Modelica.Blocks.Interfaces.RealOutput"/>
    </ScalarVariable>
    <!-- Index for next variable = 24 -->
    <ScalarVariable
      name="y[2]"
      valueReference="335544321"
      description="Systems real output"
      causality="output">
      <Real
        declaredType="Modelica.Blocks.Interfaces.RealOutput"/>
    </ScalarVariable>
    <!-- Index for next variable = 25 -->
    <ScalarVariable
      name="system.miso[1].transferFunction[1].x_start[1]"
      valueReference="16777236"
      description="Initial or guess values of states"
      causality="parameter"
      variability="fixed">
      <Real start="0"/>
    </ScalarVariable>
    <!-- Index for next variable = 26 -->
    <ScalarVariable
      name="system.miso[1].transferFunction[1].x_start[2]"
      valueReference="16777237"
      description="Initial or guess values of states"
      causality="parameter"
      variability="fixed">
      <Real start="0"/>
    </ScalarVariable>
    <!-- Index for next variable = 27 -->
    <ScalarVariable
      name="system.miso[1].transferFunction[1].y_start"
      valueReference="16777238"
      description="Initial value of output (derivatives of y are zero up to nx-1-th derivative)"
      causality="parameter"
      variability="fixed">
      <Real start="0"/>
    </ScalarVariable>
    <!-- Index for next variable = 28 -->
    <ScalarVariable
      name="system.miso[1].transferFunction[1].x_scaled[1]"
      valueReference="33554432"
      description="Scaled vector x"
      initial="exact">
      <Real start="0.0"
        derivative="30"/>
    </ScalarVariable>
    <!-- Index for next variable = 29 -->
    <ScalarVariable
      name="der(system.miso[1].transferFunction[1].x_scaled[1])"
      valueReference="587202560"
      description="der(Scaled vector x)">
      <Real derivative="28"/>
    </ScalarVariable>
    <!-- Index for next variable = 30 -->
    <ScalarVariable
      name="system.miso[1].transferFunction[1].x_scaled[2]"
      valueReference="33554433"
      description="Scaled vector x"
      initial="exact">
      <Real start="0.0"/>
    </ScalarVariable>
    <!-- Index for next variable = 31 -->
    <ScalarVariable
      name="der(system.miso[1].transferFunction[1].x_scaled[2])"
      valueReference="587202561"
      description="der(Scaled vector x)">
      <Real derivative="30"/>
    </ScalarVariable>
    <!-- Index for next variable = 32 -->
    <ScalarVariable
      name="system.miso[1].transferFunction[2].x_start[1]"
      valueReference="16777239"
      description="Initial or guess values of states"
      causality="parameter"
      variability="fixed">
      <Real start="0"/>
    </ScalarVariable>
    <!-- Index for next variable = 33 -->
    <ScalarVariable
      name="system.miso[1].transferFunction[2].x_start[2]"
      valueReference="16777240"
      description="Initial or guess values of states"
      causality="parameter"
      variability="fixed">
      <Real start="0"/>
    </ScalarVariable>
    <!-- Index for next variable = 34 -->
    <ScalarVariable
      name="system.miso[1].transferFunction[2].y_start"
      valueReference="16777241"
      description="Initial value of output (derivatives of y are zero up to nx-1-th derivative)"
      causality="parameter"
      variability="fixed">
      <Real start="0"/>
    </ScalarVariable>
    <!-- Index for next variable = 35 -->
    <ScalarVariable
      name="system.miso[1].transferFunction[2].x_scaled[1]"
      valueReference="33554434"
      description="Scaled vector x"
      initial="exact">
      <Real start="0.0"
        derivative="37"/>
    </ScalarVariable>
    <!-- Index for next variable = 36 -->
    <ScalarVariable
      name="der(system.miso[1].transferFunction[2].x_scaled[1])"
      valueReference="587202562"
      description="der(Scaled vector x)">
      <Real derivative="35"/>
    </ScalarVariable>
    <!-- Index for next variable = 37 -->
    <ScalarVariable
      name="system.miso[1].transferFunction[2].x_scaled[2]"
      valueReference="33554435"
      description="Scaled vector x"
      initial="exact">
      <Real start="0.0"/>
    </ScalarVariable>
    <!-- Index for next variable = 38 -->
    <ScalarVariable
      name="der(system.miso[1].transferFunction[2].x_scaled[2])"
      valueReference="587202563"
      description="der(Scaled vector x)">
      <Real derivative="37"/>
    </ScalarVariable>
    <!-- Index for next variable = 39 -->
    <ScalarVariable
      name="system.miso[1].add.significantDigits"
      valueReference="16777242"
      description="Number of significant digits to be shown in dynamic diagram layer for y"
      causality="parameter"
      variability="fixed">
      <Integer min="1"
        start="5"/>
    </ScalarVariable>
    <!-- Index for next variable = 40 -->
    <ScalarVariable
      name="system.miso[1].add.k[1]"
      valueReference="16777243"
      description="Input gains"
      causality="parameter"
      variability="fixed">
      <Real start="1"/>
    </ScalarVariable>
    <!-- Index for next variable = 41 -->
    <ScalarVariable
      name="system.miso[1].add.k[2]"
      valueReference="16777244"
      description="Input gains"
      causality="parameter"
      variability="fixed">
      <Real start="1"/>
    </ScalarVariable>
    <!-- Index for next variable = 42 -->
    <ScalarVariable
      name="system.miso[2].transferFunction[1].x_start[1]"
      valueReference="16777245"
      description="Initial or guess values of states"
      causality="parameter"
      variability="fixed">
      <Real start="0"/>
    </ScalarVariable>
    <!-- Index for next variable = 43 -->
    <ScalarVariable
      name="system.miso[2].transferFunction[1].x_start[2]"
      valueReference="16777246"
      description="Initial or guess values of states"
      causality="parameter"
      variability="fixed">
      <Real start="0"/>
    </ScalarVariable>
    <!-- Index for next variable = 44 -->
    <ScalarVariable
      name="system.miso[2].transferFunction[1].y_start"
      valueReference="16777247"
      description="Initial value of output (derivatives of y are zero up to nx-1-th derivative)"
      causality="parameter"
      variability="fixed">
      <Real start="0"/>
    </ScalarVariable>
    <!-- Index for next variable = 45 -->
    <ScalarVariable
      name="system.miso[2].transferFunction[1].x_scaled[1]"
      valueReference="33554436"
      description="Scaled vector x"
      initial="exact">
      <Real start="0.0"
        derivative="47"/>
    </ScalarVariable>
    <!-- Index for next variable = 46 -->
    <ScalarVariable
      name="der(system.miso[2].transferFunction[1].x_scaled[1])"
      valueReference="587202564"
      description="der(Scaled vector x)">
      <Real derivative="45"/>
    </ScalarVariable>
    <!-- Index for next variable = 47 -->
    <ScalarVariable
      name="system.miso[2].transferFunction[1].x_scaled[2]"
      valueReference="33554437"
      description="Scaled vector x"
      initial="exact">
      <Real start="0.0"/>
    </ScalarVariable>
    <!-- Index for next variable = 48 -->
    <ScalarVariable
      name="der(system.miso[2].transferFunction[1].x_scaled[2])"
      valueReference="587202565"
      description="der(Scaled vector x)">
      <Real derivative="47"/>
    </ScalarVariable>
    <!-- Index for next variable = 49 -->
    <ScalarVariable
      name="system.miso[2].transferFunction[2].x_start[1]"
      valueReference="16777248"
      description="Initial or guess values of states"
      causality="parameter"
      variability="fixed">
      <Real start="0"/>
    </ScalarVariable>
    <!-- Index for next variable = 50 -->
    <ScalarVariable
      name="system.miso[2].transferFunction[2].x_start[2]"
      valueReference="16777249"
      description="Initial or guess values of states"
      causality="parameter"
      variability="fixed">
      <Real start="0"/>
    </ScalarVariable>
    <!-- Index for next variable = 51 -->
    <ScalarVariable
      name="system.miso[2].transferFunction[2].y_start"
      valueReference="16777250"
      description="Initial value of output (derivatives of y are zero up to nx-1-th derivative)"
      causality="parameter"
      variability="fixed">
      <Real start="0"/>
    </ScalarVariable>
    <!-- Index for next variable = 52 -->
    <ScalarVariable
      name="system.miso[2].transferFunction[2].x_scaled[1]"
      valueReference="33554438"
      description="Scaled vector x"
      initial="exact">
      <Real start="0.0"
        derivative="54"/>
    </ScalarVariable>
    <!-- Index for next variable = 53 -->
    <ScalarVariable
      name="der(system.miso[2].transferFunction[2].x_scaled[1])"
      valueReference="587202566"
      description="der(Scaled vector x)">
      <Real derivative="52"/>
    </ScalarVariable>
    <!-- Index for next variable = 54 -->
    <ScalarVariable
      name="system.miso[2].transferFunction[2].x_scaled[2]"
      valueReference="33554439"
      description="Scaled vector x"
      initial="exact">
      <Real start="0.0"/>
    </ScalarVariable>
    <!-- Index for next variable = 55 -->
    <ScalarVariable
      name="der(system.miso[2].transferFunction[2].x_scaled[2])"
      valueReference="587202567"
      description="der(Scaled vector x)">
      <Real derivative="54"/>
    </ScalarVariable>
    <!-- Index for next variable = 56 -->
    <ScalarVariable
      name="system.miso[2].add.significantDigits"
      valueReference="16777251"
      description="Number of significant digits to be shown in dynamic diagram layer for y"
      causality="parameter"
      variability="fixed">
      <Integer min="1"
        start="5"/>
    </ScalarVariable>
    <!-- Index for next variable = 57 -->
    <ScalarVariable
      name="system.miso[2].add.k[1]"
      valueReference="16777252"
      description="Input gains"
      causality="parameter"
      variability="fixed">
      <Real start="1"/>
    </ScalarVariable>
    <!-- Index for next variable = 58 -->
    <ScalarVariable
      name="system.miso[2].add.k[2]"
      valueReference="16777253"
      description="Input gains"
      causality="parameter"
      variability="fixed">
      <Real start="1"/>
    </ScalarVariable>
  </ModelVariables>
  <ModelStructure>
    <Outputs>
      <Unknown index="23"
        dependencies="30 37"
        dependenciesKind="fixed fixed"/>
      <Unknown index="24"
        dependencies="47 54"
        dependenciesKind="fixed fixed"/>
    </Outputs>
    <Derivatives>
      <Unknown index="29"
        dependencies="21 28 30"
        dependenciesKind="fixed fixed fixed"/>
      <Unknown index="31"
        dependencies="28"
        dependenciesKind="fixed"/>
      <Unknown index="36"
        dependencies="22 35 37"
        dependenciesKind="fixed fixed fixed"/>
      <Unknown index="38"
        dependencies="35"
        dependenciesKind="fixed"/>
      <Unknown index="46"
        dependencies="21 45 47"
        dependenciesKind="fixed fixed fixed"/>
      <Unknown index="48"
        dependencies="45"
        dependenciesKind="fixed"/>
      <Unknown index="53"
        dependencies="22 52 54"
        dependenciesKind="fixed fixed fixed"/>
      <Unknown index="55"
        dependencies="52"
        dependenciesKind="fixed"/>
    </Derivatives>
    <InitialUnknowns>
      <Unknown index="23"
        dependencies="1 2 5 6 7 8 9 10 17 18 30 37 40 41"
        dependenciesKind="dependent dependent dependent dependent dependent dependent dependent dependent dependent dependent dependent dependent dependent dependent"/>
      <Unknown index="24"
        dependencies="3 4 11 12 13 14 15 16 19 20 47 54 57 58"
        dependenciesKind="dependent dependent dependent dependent dependent dependent dependent dependent dependent dependent dependent dependent dependent dependent"/>
      <Unknown index="29"
        dependencies="5 6 7 21 28 30"
        dependenciesKind="dependent dependent dependent dependent dependent dependent"/>
      <Unknown index="31"
        dependencies="28"
        dependenciesKind="dependent"/>
      <Unknown index="36"
        dependencies="8 9 10 22 35 37"
        dependenciesKind="dependent dependent dependent dependent dependent dependent"/>
      <Unknown index="38"
        dependencies="35"
        dependenciesKind="dependent"/>
      <Unknown index="46"
        dependencies="11 12 13 21 45 47"
        dependenciesKind="dependent dependent dependent dependent dependent dependent"/>
      <Unknown index="48"
        dependencies="45"
        dependenciesKind="dependent"/>
      <Unknown index="53"
        dependencies="14 15 16 22 52 54"
        dependenciesKind="dependent dependent dependent dependent dependent dependent"/>
      <Unknown index="55"
        dependencies="52"
        dependenciesKind="dependent"/>
    </InitialUnknowns>
  </ModelStructure>
</fmiModelDescription>
